auth_toolkit_fastapi-0.1.0.dist-info/licenses/LICENSE
core/__init__.py
core/auth.py
core/config.py
core/defaults.py
core/methods.py
core/tokens.py
exceptions/__init__.py
exceptions/jwt_error.py
plugins/__init__.py
plugins/websocket/__init__.py
plugins/websocket/ws_plugin.py
auth_toolkit_fastapi-0.1.0.dist-info/METADATA
auth_toolkit_fastapi-0.1.0.dist-info/WHEEL
auth_toolkit_fastapi-0.1.0.dist-info/top_level.txt
auth_toolkit_fastapi-0.1.0.dist-info/RECORD
