Metadata-Version: 2.4
Name: auth-toolkit-fastapi
Version: 0.1.0
Summary: Flexible authentication fastapi toolkit with websocet if u need
Home-page: https://github.com/linecodesxx/auth_toolkit
Author: linecodesx
Author-email: linecodesx <feyte11@icloud.com>
License: MIT
Project-URL: Homepage, https://github.com/linecodesxx/auth_toolkit
Project-URL: Repository, https://github.com/linecodesxx/auth_toolkit
Classifier: Development Status :: 3 - Alpha
Classifier: Intended Audience :: Developers
Classifier: License :: OSI Approved :: MIT License
Classifier: Operating System :: OS Independent
Classifier: Programming Language :: Python :: 3
Classifier: Programming Language :: Python :: 3.8
Classifier: Programming Language :: Python :: 3.9
Classifier: Programming Language :: Python :: 3.10
Classifier: Programming Language :: Python :: 3.11
Requires-Python: >=3.8
License-File: LICENSE
Requires-Dist: jwt
Requires-Dist: pwdlib>=1.0.0
Provides-Extra: websocket
Requires-Dist: fastapi>=0.100.0; extra == "websocket"
Dynamic: author
Dynamic: home-page
Dynamic: license-file
Dynamic: requires-python
